Symple/__init__.py
Symple/Nodes/Node.py
Symple/Nodes/Tensor.py
Symple/Nodes/Utils.py
Symple/Nodes/__init__.py
Symple/Nodes/Ops/Add.py
Symple/Nodes/Ops/MSE.py
Symple/Nodes/Ops/Matmul.py
Symple/Nodes/Ops/Relu.py
Symple/Nodes/Ops/SoftmaxWithCrossEntropy.py
Symple/Nodes/Ops/Sub.py
Symple/Nodes/Ops/__init__.py
Symple/tests/Node/__init__.py
Symple/tests/Node/test_node.py
Symple/tests/Node/Ops/Helpers.py
Symple/tests/Node/Ops/__init__.py
Symple/tests/Node/Ops/test_add.py
Symple/tests/Node/Ops/test_mse.py
Symple/tests/Node/Ops/test_softmax_with_crossentropy.py
Symple/tests/Node/Ops/test_sub.py
Symple-0.0.3.dist-info/METADATA
Symple-0.0.3.dist-info/RECORD
Symple-0.0.3.dist-info/WHEEL
Symple-0.0.3.dist-info/top_level.txt
