Metadata-Version: 2.1
Name: Symple
Version: 0.0.3
Summary: Simple Automatic Differentiation in Python 
Home-page: https://github.com/harveyslash/Sympyle
Author: Harshvardhan Gupta
Author-email: theharshvardhangupta@gmail.com
License: GNU GENERAL PUBLIC LICENSE
Platform: UNKNOWN
Requires-Dist: numpy
